{
  "intro": {
    "titleSuffix": "Übersicht",
    "welcome": "Willkommen im Kurs {label}!",
    "description": "Hier findest du alle Materialien, Erklärungen und Übungen zu den Themen des Schuljahres."
  },
  "currentTopic": {
    "heading": "Aktuelles Thema"
  },
  "worksheets": {
    "title": "Aktuelle Aufgaben",
    "actions": {
      "web": "Online öffnen",
      "pdf": "PDF herunterladen",
      "pdfSolution": "Lösung herunterladen"
    }
  },
  "roadmap": {
    "heading": "Roadmap",
    "chaptersAriaLabel": "Chapters for {label}"
  }
}